Metadata-Version: 2.1
Name: itoptop
Version: 1.0.10
Summary: iTOP API Python Lib
Home-page: https://github.com/jonatasrenan/itoptop/
Author: Jonatas Renan
Author-email: jonatasrenan@gmail.com
License: UNKNOWN
Keywords: itop api concurrent datamodel
Platform: UNKNOWN
Classifier: Development Status :: 5 - Production/Stable
Classifier: Environment :: Console
Classifier: Intended Audience :: Developers
Classifier: License :: OSI Approved :: GNU General Public License v3 (GPLv3)
Classifier: Programming Language :: Python :: 3
Classifier: Topic :: Software Development :: Libraries :: Python Modules
Classifier: Topic :: Utilities
